ranpick/__init__.py
ranpick/rannumber.py
ranpick/ranrandom.py
ranpick-3.1.0.dist-info/licenses/LICENSE
ranpick-3.1.0.dist-info/METADATA
ranpick-3.1.0.dist-info/WHEEL
ranpick-3.1.0.dist-info/top_level.txt
ranpick-3.1.0.dist-info/RECORD
