Metadata-Version: 2.4
Name: ranpick
Version: 3.1.0
Summary: A high-entropy random number generation library
Author: rainy58
Author-email: yhg4908@naver.com
Project-URL: Issues, https://github.com/yhg4908/ranpick.py/issues
Project-URL: Repository, https://github.com/yhg4908/ranpick.py
Keywords: random number generation entropy ranpick list Probability
Classifier: Development Status :: 5 - Production/Stable
Classifier: Intended Audience :: Developers
Classifier: License :: OSI Approved :: MIT License
Classifier: Programming Language :: Python :: 3
Classifier: Programming Language :: Python :: 3.7
Classifier: Programming Language :: Python :: 3.8
Classifier: Programming Language :: Python :: 3.9
Classifier: Programming Language :: Python :: 3.10
Classifier: Programming Language :: Python :: 3.11
Classifier: Programming Language :: Python :: 3.12
Classifier: Programming Language :: Python :: 3.13
Requires-Python: >=3.7
License-File: LICENSE
Dynamic: author
Dynamic: author-email
Dynamic: classifier
Dynamic: description
Dynamic: description-content-type
Dynamic: keywords
Dynamic: license-file
Dynamic: project-url
Dynamic: requires-python
Dynamic: summary
